<Root><Handbook><Announcement><TxtStyle1>Дополнительные информационные сообщения</TxtStyle1></Announcement><Announcement><TxtStyle7>Задержки</TxtStyle7></Announcement><Announcement><TxtStyle2>Задержка вылета рейса (15 минут и более) при нахождении пассажиров на борту (СБ или КВС) (дневной/ночной рейс)</TxtStyle2></Announcement><Announcement><TxtStyle0_Russian>Дамы и господа!</TxtStyle0_Russian><TxtStyle0_German>Meine Damen und Herren!</TxtStyle0_German><Separator>@</Separator></Announcement><Announcement><TxtStyle0_Russian>Говорит старший бортпроводник экипажа/командир корабля.</TxtStyle0_Russian><TxtStyle0_German>Hier spricht der (die) Chefflugbegleiter(in)/ der Flugkapitän.</TxtStyle0_German><Separator>@</Separator></Announcement><Announcement><TxtStyle0_Russian>@</TxtStyle0_Russian><TxtStyle0_German>БП: Der Flugkapitän hat uns folgendes mitgeteilt.</TxtStyle0_German><Separator>@</Separator></Announcement><Announcement><TxtStyle0_Russian>Наш вылет задерживается на …часов …минут … [указать причину]:</TxtStyle0_Russian><TxtStyle0_German>Unser Flug hat sich um (eine Stunde) …Stunden und …Minuten verzögert. Der Grund für die Verspätung ist… [указать причину]:</TxtStyle0_German><Separator>@</Separator></Announcement><Announcement><TxtStyle6_Russian>по метеоусловиям аэропорта… [название аэропорта];</TxtStyle6_Russian><TxtStyle6_German>schlechte Wetterbedingungen am Flughafen… [название аэропорта];</TxtStyle6_German><Separator>@</Separator></Announcement><Announcement><TxtStyle6_Russian>в связи с загрузкой багажа и груза службами аэропорта;</TxtStyle6_Russian><TxtStyle6_German>die Gepäck-und-Frachtabfertigung von den Flughafenbodendiensten;</TxtStyle6_German><Separator>@</Separator></Announcement><Announcement><TxtStyle6_Russian>в связи с ожиданием группы транзитных пассажиров;</TxtStyle6_Russian><TxtStyle6_German>die verspätete Ankunft von Transitreisenden;</TxtStyle6_German><Separator>@</Separator></Announcement><Announcement><TxtStyle6_Russian>в связи со снятием багажа пассажира, не явившегося на рейс;</TxtStyle6_Russian><TxtStyle6_German>die Entfernung von Gepäck eines Reisenden, der sich nicht an Bord des Flugzeugs befindet;</TxtStyle6_German><Separator>@</Separator></Announcement><Announcement><TxtStyle6_Russian>в связи с забастовкой служащих аэропорта;</TxtStyle6_Russian><TxtStyle6_German>der Streik am Flughafen;</TxtStyle6_German><Separator>@</Separator></Announcement><Announcement><TxtStyle6_Russian>в связи с изменением графика выполнения полетов;</TxtStyle6_Russian><TxtStyle6_German>die Änderung des Flugplans;</TxtStyle6_German><Separator>@</Separator></Announcement><Announcement><TxtStyle6_Russian>в связи с подготовкой самолета к рейсу. Аэрофлот принимает все возможные меры для нашего скорейшего вылета;</TxtStyle6_Russian><TxtStyle6_German>die Flugzeugabfertiung. Aeroflot tut ihr Bestes, damit wir sobald wie möglich starten können;</TxtStyle6_German><Separator>@</Separator></Announcement><Announcement><TxtStyle6_Russian>в связи с интенсивностью воздушного движения в зоне аэропорта;</TxtStyle6_Russian><TxtStyle6_German>die Luftverkehrsdichte im Flughafenbereich;</TxtStyle6_German><Separator>@</Separator></Announcement><Announcement><TxtStyle6_Russian>в связи с ожиданием разрешения на вылет, связанным с большой загруженностью аэропорта.</TxtStyle6_Russian><TxtStyle6_German>die anhängige Abflugfreigabe wegen der hohen Arbeitsbelastung am Flughafen.</TxtStyle6_German><Separator>@</Separator></Announcement><Announcement><TxtStyle0_Russian>Просим вас… [выбрать необходимое]:</TxtStyle0_Russian><TxtStyle0_German>Bitte… [выбрать необходимое]:</TxtStyle0_German><Separator>@</Separator></Announcement><Announcement><TxtStyle6_Russian>оставаться на своих местах с застегнутыми ремнями безопасности;</TxtStyle6_Russian><TxtStyle6_German>bleiben Sie angeschnallt sitzen;</TxtStyle6_German><Separator>@</Separator></Announcement><Announcement><TxtStyle6_Russian>оставаться на своих местах. Через несколько минут вам будут предложены напитки (и питание);</TxtStyle6_Russian><TxtStyle6_German>bleiben Sie sitzen. Wir werden in Kürze Getränke (und Essen) servieren;</TxtStyle6_German><Separator>@</Separator></Announcement><Announcement><TxtStyle6_Russian>взять с собой ручную кладь и пройти в зал ожидания. Вы будете приглашены на посадку, как только вылет самолета будет возможным. Просьба сохранять посадочный талон.</TxtStyle6_Russian><TxtStyle6_German>Nehmen Sie Ihr Handgepäck und gehen Sie zum Wartesaal. Sobald das Flugzeug abflugbereit ist, werden wir Sie zum Einsteigen auffordern. Bitte halten Sie Ihre Bordkarte bereit.</TxtStyle6_German><Separator>@</Separator></Announcement><Announcement><TxtStyle0_Russian>Приносим вам свои извинения за причиненные неудобства.</TxtStyle0_Russian><TxtStyle0_German>Wir entschuldigen uns dafür, und bitten um Ihr Verständnis.</TxtStyle0_German><Separator>@</Separator></Announcement><Announcement><TxtStyle0_Russian>Наземные службы в… [название пункта назначения] предупреждены о задержке вылета и окажут вам необходимую помощь и содействие.</TxtStyle0_Russian><TxtStyle0_German>Bodenpersonal am Flughafen in… [название пункта назначения] sind über die Verspätung informiert worden und werden ihr Bestes tun, um Ihnen bei allen Fragen zu helfen.</TxtStyle0_German><Separator>@</Separator></Announcement><Announcement><TxtStyle0_Russian>Благодарим (благодарю) за внимание.</TxtStyle0_Russian><TxtStyle0_German>Danke.</TxtStyle0_German><Separator>@</Separator></Announcement><Announcement><TxtStyle2>Возвращение на место стоянки перед вылетом (КВС или СБ по указанию КВС) (дневной/ночной рейс)</TxtStyle2></Announcement><Announcement><TxtStyle0_Russian>Дамы и господа!</TxtStyle0_Russian><TxtStyle0_German>Meine Damen und Herren!</TxtStyle0_German><Separator>@</Separator></Announcement><Announcement><TxtStyle0_Russian>Говорит командир корабля. (Командир корабля сообщил, что…) [выбрать необходимое]:</TxtStyle0_Russian><TxtStyle0_German>Hier spricht Ihr Kapitän. (Der Kapitän teilt folgendes mit…) [выбрать необходимое]:</TxtStyle0_German><Separator>@</Separator></Announcement><Announcement><TxtStyle6_Russian>По метеоусловиям аэропорта… [название аэропорта];</TxtStyle6_Russian><TxtStyle6_German>Wegen der Wetterbedingungen am Flughafen… [название аэропорта];</TxtStyle6_German><Separator>@</Separator></Announcement><Announcement><TxtStyle6_Russian>В связи с производственными причинами</TxtStyle6_Russian><TxtStyle6_German>Aus betriebsbedingten Gründen</TxtStyle6_German><Separator>@</Separator></Announcement><Announcement><TxtStyle0_Russian>мы вынуждены вернуться на место стоянки.</TxtStyle0_Russian><TxtStyle0_German>kehrt das Flugzeug nun auf seinen Halteplatz zurück.</TxtStyle0_German><Separator>@</Separator></Announcement><Announcement><TxtStyle0_Russian>Прошу вас оставаться на своих местах с застегнутыми ремнями безопасности.</TxtStyle0_Russian><TxtStyle0_German>Bitte bleiben Sie angeschnallt sitzen.</TxtStyle0_German><Separator>@</Separator></Announcement><Announcement><TxtStyle0_Russian>Как только будет получена дополнительная информация, мы вам ее сообщим.</TxtStyle0_Russian><TxtStyle0_German>Weitere Informationen folgen.</TxtStyle0_German><Separator>@</Separator></Announcement><Announcement><TxtStyle0_Russian>Приносим вам свои извинения за причиненные неудобства.</TxtStyle0_Russian><TxtStyle0_German>Wir entschuldigen uns dafür, und bitten um Ihr Verständnis.</TxtStyle0_German><Separator>@</Separator></Announcement><Announcement><TxtStyle0_Russian>Благодарю (благодарим) за внимание.</TxtStyle0_Russian><TxtStyle0_German>Danke.</TxtStyle0_German><Separator>@</Separator></Announcement><Announcement><TxtStyle2>Заправка топливом с пассажирами на борту (СБ) (дневной/ночной рейс)</TxtStyle2></Announcement><Announcement><TxtStyle0_Russian>Дамы и господа!</TxtStyle0_Russian><TxtStyle0_German>Meine Damen und Herren!</TxtStyle0_German><Separator>@</Separator></Announcement><Announcement><TxtStyle0_Russian>В настоящий момент наш самолет заправляют топливом.</TxtStyle0_Russian><TxtStyle0_German>Das Flugzeug wird derzeit aufgetankt.</TxtStyle0_German><Separator>@</Separator></Announcement><Announcement><TxtStyle0_Russian>Просим вас отстегнуть ремни безопасности и оставаться на своих местах.</TxtStyle0_Russian><TxtStyle0_German>Bitte öffnen Sie Ihren Sicherheitsgurt und bleiben Sie bitte sitzen.</TxtStyle0_German><Separator>@</Separator></Announcement><Announcement><TxtStyle0_Russian>Аварийные выходы и проходы в салонах должны быть свободными.</TxtStyle0_Russian><TxtStyle0_German>Alle Gänge und Notausgänge müssen von sämtlichen Gepäckstücken vollständig frei bleiben.</TxtStyle0_German><Separator>@</Separator></Announcement><Announcement><TxtStyle0_Russian>Мы сообщим вам об окончании заправки.</TxtStyle0_Russian><TxtStyle0_German>Wir werden Ihnen Bescheid geben, sobald die Maschine aufgetankt ist.</TxtStyle0_German><Separator>@</Separator></Announcement><Announcement><TxtStyle0_Russian>Благодарим за внимание.</TxtStyle0_Russian><TxtStyle0_German>Danke.</TxtStyle0_German><Separator>@</Separator></Announcement><Announcement><TxtStyle3>Окончание заправки топливом с пассажирами на борту (СБ) (дневной/ночной рейс)</TxtStyle3></Announcement><Announcement><TxtStyle0_Russian>Дамы и господа!</TxtStyle0_Russian><TxtStyle0_German>Meine Damen und Herren!</TxtStyle0_German><Separator>@</Separator></Announcement><Announcement><TxtStyle0_Russian>Заправка самолета закончена.</TxtStyle0_Russian><TxtStyle0_German>Die Maschine ist nun aufgetankt.</TxtStyle0_German><Separator>@</Separator></Announcement><Announcement><TxtStyle0_Russian>Мы рассчитываем вылететь через …минут/несколько минут.</TxtStyle0_Russian><TxtStyle0_German>Wir werden in …Minuten starten.</TxtStyle0_German><Separator>@</Separator></Announcement><Announcement><TxtStyle0_Russian>Благодарим за внимание.</TxtStyle0_Russian><TxtStyle0_German>Danke.</TxtStyle0_German><Separator>@</Separator></Announcement><Announcement><TxtStyle2>Задержка посадки ВС (СБ по указанию КВС) (дневной/ночной рейс)</TxtStyle2></Announcement><Announcement><TxtStyle0_Russian>Дамы и господа!</TxtStyle0_Russian><TxtStyle0_German>Meine Damen und Herren!</TxtStyle0_German><Separator>@</Separator></Announcement><Announcement><TxtStyle0_Russian>Командир корабля сообщил, что наше прибытие в аэропорт… [название аэропорта] задерживается… [выбрать необходимое]:</TxtStyle0_Russian><TxtStyle0_German>Der Kapitän teilt uns folgendes mit. Unsere Ankunft in… [название аэропорта] Flughafen hat sich… [выбрать необходимое]:</TxtStyle0_German><Separator>@</Separator></Announcement><Announcement><TxtStyle6_Russian>на …минут в связи с интенсивностью воздушного движения. Мы ждем разрешения на посадку;</TxtStyle6_Russian><TxtStyle6_German>im Zusammenhang mit der Luftverkehrsdichte um …Minuten verzögert. Wir warten auf die Landeerlaubnis;</TxtStyle6_German><Separator>@</Separator></Announcement><Announcement><TxtStyle6_Russian>по метеоусловиям аэропорта. Мы будем находиться в зоне ожидания, пока погодные условия не позволят нам совершить посадку.</TxtStyle6_Russian><TxtStyle6_German>wegen der schlechten Wetterbedingungen am Flughafen verzögert. Wir werden solange in der Warteschleife bleiben, bis die Wetterbedingungen eine Landung zulassen.</TxtStyle6_German><Separator>@</Separator></Announcement><Announcement><TxtStyle0_Russian>Просим вас оставаться на своих местах с застегнутыми ремнями безопасности.</TxtStyle0_Russian><TxtStyle0_German>Bitte bleiben Sie angeschnallt sitzen.</TxtStyle0_German><Separator>@</Separator></Announcement><Announcement><TxtStyle0_Russian>Приносим вам свои извинения за причиненные неудобства.</TxtStyle0_Russian><TxtStyle0_German>Wir entschuldigen uns dafür, und bitten um Ihr Verständnis.</TxtStyle0_German><Separator>@</Separator></Announcement><Announcement><TxtStyle0_Russian>Благодарим за внимание.</TxtStyle0_Russian><TxtStyle0_German>Danke.</TxtStyle0_German><Separator>@</Separator></Announcement><Announcement><TxtStyle2>Во время ожидания парковки ВС (КВС) (дневной/ночной рейс)</TxtStyle2></Announcement><Announcement><TxtStyle0_Russian>Дамы и господа!</TxtStyle0_Russian><TxtStyle0_German>Meine Damen und Herren!</TxtStyle0_German><Separator>@</Separator></Announcement><Announcement><TxtStyle0_Russian>Говорит командир корабля.</TxtStyle0_Russian><TxtStyle0_German>Hier spricht Ihr Kapitän.</TxtStyle0_German><Separator>@</Separator></Announcement><Announcement><TxtStyle0_Russian>@</TxtStyle0_Russian><TxtStyle0_German>СБ: Der Kapitän teilt uns folgendes mit.</TxtStyle0_German><Separator>@</Separator></Announcement><Announcement><TxtStyle0_Russian>Мы ожидаем разрешения на парковку от служб аэропорта.</TxtStyle0_Russian><TxtStyle0_German>Wir warten auf die Erlaubnis, von den Flughafenbodendiensten unsere entgültige Parkposition einzunehmen.</TxtStyle0_German><Separator>@</Separator></Announcement><Announcement><TxtStyle0_Russian>Прошу вас оставаться на своих местах с застегнутыми ремнями безопасности.</TxtStyle0_Russian><TxtStyle0_German>Bitte bleiben Sie angeschnallt sitzen.</TxtStyle0_German><Separator>@</Separator></Announcement><Announcement><TxtStyle0_Russian>Приносим вам свои извинения за причиненные неудобства.</TxtStyle0_Russian><TxtStyle0_German>Wir entschuldigen uns dafür, und bitten um Ihr Verständnis.</TxtStyle0_German><Separator>@</Separator></Announcement><Announcement><TxtStyle0_Russian>Благодарю за внимание.</TxtStyle0_Russian><TxtStyle0_German>Danke.</TxtStyle0_German><Separator>@</Separator></Announcement><Announcement><TxtStyle2>Во время ожидания разрешения наземных служб на высадку из ВС (СБ) (дневной/ночной рейс)</TxtStyle2></Announcement><Announcement><TxtStyle0_Russian>Дамы и господа!</TxtStyle0_Russian><TxtStyle0_German>Meine Damen und Herren!</TxtStyle0_German><Separator>@</Separator></Announcement><Announcement><TxtStyle0_Russian>Мы ожидаем разрешения наземных служб аэропорта на высадку из самолета. Просим вас оставаться на своих местах.</TxtStyle0_Russian><TxtStyle0_German>Wir warten auf die Aussteigenerlaubnis. Wir bitten Sie auf Ihren Plätzen zu bleiben.</TxtStyle0_German><Separator>@</Separator></Announcement><Announcement><TxtStyle0_Russian>К выходу мы вас пригласим.</TxtStyle0_Russian><TxtStyle0_German>Wir werden Sie zum Aussteigen auffordern.</TxtStyle0_German><Separator>@</Separator></Announcement><Announcement><TxtStyle0_Russian>Благодарим за внимание.</TxtStyle0_Russian><TxtStyle0_German>Danke.</TxtStyle0_German><Separator>@</Separator></Announcement><Announcement><TxtStyle7>Перед вылетом</TxtStyle7></Announcement><Announcement><TxtStyle2>Приветствие КВС в аэропорту вылета при открытии новой трассы (КВС) (дневной/ночной рейс)</TxtStyle2></Announcement><Announcement><TxtStyle0_Russian>Доброе утро/Добрый день/Добрый вечер, дамы и господа!</TxtStyle0_Russian><TxtStyle0_German>Guten Morgen/Tag/Abend, meine Damen und Herren!</TxtStyle0_German><Separator>@</Separator></Announcement><Announcement><TxtStyle0_Russian>Говорит командир корабля… [имя и фамилия]. От имени всего экипажа и авиакомпании «Аэрофлот – российские авиалинии» приветствую вас на борту самолета… [тип ВС].</TxtStyle0_Russian><TxtStyle0_German>Hier spricht Ihr Kapitän. Mein Name ist… [имя и фамилия]. Im Namen der gesamten Besatzung und von „Aeroflot – Russian Airlines“ begrüße ich Sie herzlich an Bord dieses/dieser… [тип ВС].</TxtStyle0_German><Separator>@</Separator></Announcement><Announcement><TxtStyle0_Russian>@</TxtStyle0_Russian><TxtStyle0_German>СБ: Der Flugkapitän… [имя и фамилия] begrüßt Sie im Namen der gesamten Besatzung und im Auftrag von „Aeroflot – Russian Airlines an Bord dieses Flugzeugs/dieser… [тип ВС].</TxtStyle0_German><Separator>@</Separator></Announcement><Announcement><TxtStyle0_Russian>Сегодня мы открываем новую трассу Москва – … [конечный пункт трассы]. (Наш рейс выполняется совместно с авиакомпанией «…» [название авиакомпании по код-шер]). Длина маршрута …километров.</TxtStyle0_Russian><TxtStyle0_German>Heute eröffnen wir eine neue Flugroute von Moskau nach… [конечный пункт трассы]. (Dieser Flug wird in Partnerschaft mit der Fluggesellschaft… [название авиакомпании по код-шер]) veranstaltet. Die Flugstrecke beträgt …Kilometer.</TxtStyle0_German><Separator>@</Separator></Announcement><Announcement><TxtStyle0_Russian>Время в пути составит …часов …минут.</TxtStyle0_Russian><TxtStyle0_German>Die gesamte Flugdauer beträgt …Stunden und …Minuten.</TxtStyle0_German><Separator>@</Separator></Announcement><Announcement><TxtStyle4>Если была задержка вылета в аэропорту (более 15 минут), см. 1.2.</TxtStyle4></Announcement><Announcement><TxtStyle0_Russian>Желаю приятного полета!</TxtStyle0_Russian><TxtStyle0_German>Ich wünsche Ihnen guten Flug.</TxtStyle0_German><Separator>@</Separator></Announcement><Announcement><TxtStyle0_Russian>@</TxtStyle0_Russian><TxtStyle0_German>СБ: Wir wünschen Ihnen guten Flug.</TxtStyle0_German><Separator>@</Separator></Announcement><Announcement><TxtStyle2>Приветствие КВС в аэропорту вылета Новый год и Рождество (КВС) (дневной/ночной рейс)</TxtStyle2></Announcement><Announcement><TxtStyle4>Читать в период с 24.12 по 08.01 включительно</TxtStyle4></Announcement><Announcement><TxtStyle0_Russian>Доброе утро/ Добрый день/ Добрый вечер, дамы и господа!</TxtStyle0_Russian><TxtStyle0_German>Guten Morgen/Tag/Abend, meine Damen und Herren!</TxtStyle0_German><Separator>@</Separator></Announcement><Announcement><TxtStyle0_Russian>Говорит командир корабля… [имя и фамилия]. Поздравляю вас с (наступающим) Новым годом и Рождеством!</TxtStyle0_Russian><TxtStyle0_German>Hier spricht Ihr Kapitän. Mein Name ist… [имя и фамилия]. Ich wünsche Ihnen allen fröhliche Weihnachten und ein glückliches Neues Jahr.</TxtStyle0_German><Separator>@</Separator></Announcement><Announcement><TxtStyle0_Russian>От имени всего экипажа и авиакомпании «Аэрофлот – российские авиалинии» приветствую вас на борту самолета… [тип ВС].</TxtStyle0_Russian><TxtStyle0_German>Im Namen der gesamten Besatzung und von „Aeroflot – Russian Airlines“ begrüße ich Sie herzlich an Bord dieses/dieser… [тип ВС].</TxtStyle0_German><Separator>@</Separator></Announcement><Announcement><TxtStyle0_Russian>@</TxtStyle0_Russian><TxtStyle0_German>СБ: Der Flugkapitän… [имя и фамилия] wünscht Ihnen allen frohe Weihnachten und ein glückliches Neues Jahr. Im Namen der gesamten Besatzung und von „Aeroflot – Russian Airlines“ begrüsst er Sie herzlich an Bord dieses Flugzeugs/dieser… [тип ВС].</TxtStyle0_German><Separator>@</Separator></Announcement><Announcement><TxtStyle0_Russian>Наш рейс выполняется по маршруту …–… (совместно с авиакомпанией «…» [название авиакомпании по код-шер]).</TxtStyle0_Russian><TxtStyle0_German>Unsere Flugroute geht heute von… nach… (in Partnerschaft mit der Fluggesellschaft… [название авиакомпании по код-шер]).</TxtStyle0_German><Separator>@</Separator></Announcement><Announcement><TxtStyle0_Russian>Время в пути составит… часов… минут.</TxtStyle0_Russian><TxtStyle0_German>Die gesamte Flugdauer beträgt… Stunden und… Minuten.</TxtStyle0_German><Separator>@</Separator></Announcement><Announcement><TxtStyle4>Если была задержка вылета в аэропорту (более 15 минут), см. 1.2.</TxtStyle4></Announcement><Announcement><TxtStyle0_Russian>Желаю приятного полета!</TxtStyle0_Russian><TxtStyle0_German>Ich wünsche Ihnen guten Flug.</TxtStyle0_German><Separator>@</Separator></Announcement><Announcement><TxtStyle0_Russian>@</TxtStyle0_Russian><TxtStyle0_German>СБ: Wir wünschen Ihnen guten Flug.</TxtStyle0_German><Separator>@</Separator></Announcement><Announcement><TxtStyle2>Приветствие СБ в аэропорту вылета Новый год и Рождество (СБ) (дневной/ночной рейс)</TxtStyle2></Announcement><Announcement><TxtStyle4>Информация читается СБ наизусть по СПГУ при открытых шторках, стоя в салоне класса Бизнес</TxtStyle4></Announcement><Announcement><TxtStyle5>*Читается в родительном падеже, например, «выдающегося композитора Игоря Стравинского», «выдающегося путешественника Николая Миклухо-Маклая», «великого полководца Александра Суворова»</TxtStyle5></Announcement><Announcement><TxtStyle4>Читать в период с 24.12 по 08.01 включительно</TxtStyle4></Announcement><Announcement><TxtStyle0_Russian>Дамы и господа!</TxtStyle0_Russian><TxtStyle0_German>Мeine Damen und Herren!</TxtStyle0_German><Separator>@</Separator></Announcement><Announcement><TxtStyle0_Russian>Меня зовут… [имя без фамилии]. Я – старший бортпроводник экипажа.</TxtStyle0_Russian><TxtStyle0_German>Mein Name ist… [имя без фамилии]. Ich bin heute Ihr(e) Chefflugbegleiter(in).</TxtStyle0_German><Separator>@</Separator></Announcement><Announcement><TxtStyle0_Russian>От имени всего экипажа поздравляю вас с (наступающим) Новым годом и Рождеством! Желаю вам в новом году здоровья, удачи, благополучия, хороших новостей, ярких идей, успешных начинаний!</TxtStyle0_Russian><TxtStyle0_German>Im Namen der Crew gratuliere ich Ihnen zum Weihnachtsfest und Neujahr! Ich wünsche Ihnen gute Gesundheit, viel Erfolg und Wohlergehen.</TxtStyle0_German><Separator>@</Separator></Announcement><Announcement><TxtStyle0_Russian>Приветствую вас на борту нашего самолета, который носит имя… [указать определение рода деятельности из Приложения №2]… [имя и фамилия человека, в честь которого названо ВС*].</TxtStyle0_Russian><TxtStyle0_German>Willkommen an Bord dieser Aeroflot Maschine. Sie trägt den Namen… [указать определение рода деятельности из Приложения №2]… [имя и фамилия человека, в честь которого названо ВС].</TxtStyle0_German><Separator>@</Separator></Announcement><Announcement><TxtStyle0_Russian>Приоритетом нашей компании является ваша безопасность и комфорт. [выбрать из вариантов]:</TxtStyle0_Russian><TxtStyle0_German>Ihre Sicherheit und Ihr Komfort sind für uns oberste Priorität. [выбрать из вариантов]:</TxtStyle0_German><Separator>@</Separator></Announcement><Announcement><TxtStyle6_Russian>Я и мои коллеги сделаем все возможное, чтобы сегодняшний полет был приятным для вас.</TxtStyle6_Russian><TxtStyle6_German>Meine Kollegen und ich (Wir) werden unser Bestes tun, um Ihren Aufenthalt an Bord so angenehm wie möglich zu gestalten.</TxtStyle6_German><Separator>@</Separator></Announcement><Announcement><TxtStyle6_Russian>Я и мои коллеги всегда к вашим услугам и рады оказать вам заботу и внимание.</TxtStyle6_Russian><TxtStyle6_German>Meine Mitarbeiter und ich (Wir) stehen Ihnen jederzeit zu Diensten und sind Ihnen in allen Fragen gerne behilflich.</TxtStyle6_German><Separator>@</Separator></Announcement><Announcement><TxtStyle6_Russian>Я и мои коллеги сделаем все возможное, чтобы сегодняшний полет доставил вам удовольствие.</TxtStyle6_Russian><TxtStyle6_German>Meine Kollegen und ich (Wir) werden unser Bestes tun, damit der heutige Flug Ihnen Spaß mächte.</TxtStyle6_German><Separator>@</Separator></Announcement><Announcement><TxtStyle0_Russian>Уважаемые постоянные клиенты – участники программы «Аэрофлот Бонус» и бонусных программ альянса SkyTeam уровней Elite и Elite Plus! Мы благодарим вас за выбор авиакомпаний Группы Аэрофлот.</TxtStyle0_Russian><TxtStyle0_German>Sehr geehrte Stammkunden – Mitglieder des Vielfliegerprogramms „Aeroflot Bonus” und anderer Bonusprogramme der Allianz SkyTeam der Niveaus Elite und Elite Plus! Wir danken Ihnen für die Auswahl von Fluggesellschaften der Aeroflot-Gruppe.</TxtStyle0_German><Separator>@</Separator></Announcement><Announcement><TxtStyle0_Russian>Благодарим за внимание.</TxtStyle0_Russian><TxtStyle0_German>Danke für Ihre Aufmerksamkeit.</TxtStyle0_German><Separator>@</Separator></Announcement><Announcement><TxtStyle2>Перед посадкой пассажиров в транзитном аэропорту (СБ) (дневной/ночной рейс)</TxtStyle2></Announcement><Announcement><TxtStyle0_Russian>Дамы и господа!</TxtStyle0_Russian><TxtStyle0_German>Meine Damen und Herren!</TxtStyle0_German><Separator>@</Separator></Announcement><Announcement><TxtStyle0_Russian>Мы начинаем посадку пассажиров из аэропорта… [название аэропорта].</TxtStyle0_Russian><TxtStyle0_German>In Kürze werden Reisende vom Flughafen… [название аэропорта] zusteigen.</TxtStyle0_German><Separator>@</Separator></Announcement><Announcement><TxtStyle0_Russian>Просим вас занять место, номер которого указан в вашем посадочном талоне.</TxtStyle0_Russian><TxtStyle0_German>Bitte kehren Sie zu Ihrem Sitzplatz zurück. Ihre Platznummer steht auf Ihrer Bordkarte.</TxtStyle0_German><Separator>@</Separator></Announcement><Announcement><TxtStyle0_Russian>Благодарим за внимание.</TxtStyle0_Russian><TxtStyle0_German>Danke.</TxtStyle0_German><Separator>@</Separator></Announcement><Announcement><TxtStyle2>Подсчет пассажиров (СБ) (дневной/ночной рейс)</TxtStyle2></Announcement><Announcement><TxtStyle0_Russian>Дамы и господа!</TxtStyle0_Russian><TxtStyle0_German>Meine Damen und Herren!</TxtStyle0_German><Separator>@</Separator></Announcement><Announcement><TxtStyle0_Russian>Наш рейс… [номер рейса] выполняется по маршруту …–… (совместно с авиакомпанией «…» [название авиакомпании по код-шер]).</TxtStyle0_Russian><TxtStyle0_German>Unser Flug… [номер рейса] von… nach… (wird in Partnerschaft mit… [название авиакомпании по код-шер]) ausgeführt.</TxtStyle0_German><Separator>@</Separator></Announcement><Announcement><TxtStyle0_Russian>Нам необходимо уточнить количество пассажиров на борту.</TxtStyle0_Russian><TxtStyle0_German>Jetzt ist es nötig, die Zahl der Fluggäste an Bord festzustellen.</TxtStyle0_German><Separator>@</Separator></Announcement><Announcement><TxtStyle0_Russian>Просим вас занять свое место согласно посадочному талону и приготовить посадочный талон для дополнительной проверки.</TxtStyle0_Russian><TxtStyle0_German>Bitte nehmen Sie Ihre Sitzplätze in der Kabine laut der Bordkarten ein, und halten Sie bitte Ihre Bordkarten für eine zusätzliche Überprüfung bereit.</TxtStyle0_German><Separator>@</Separator></Announcement><Announcement><TxtStyle0_Russian>Благодарим за внимание.</TxtStyle0_Russian><TxtStyle0_German>Danke.</TxtStyle0_German><Separator>@</Separator></Announcement><Announcement><TxtStyle2>Розыск пассажира (СБ) (дневной/ночной рейс)</TxtStyle2></Announcement><Announcement><TxtStyle0_Russian>Дамы и господа!</TxtStyle0_Russian><TxtStyle0_German>Meine Damen und Herren!</TxtStyle0_German><Separator>@</Separator></Announcement><Announcement><TxtStyle0_Russian>Просим господина/госпожу… обратиться к… (бортпроводникам, персоналу…) (при выходе из самолета).</TxtStyle0_Russian><TxtStyle0_German>Dies ist ein Aufruf für Herr/Frau… Bitte melden Sie sich… (beim Bordpersonal, beim Personal nach dem Verlassen des Flugzeugs).</TxtStyle0_German><Separator>@</Separator></Announcement><Announcement><TxtStyle0_Russian>Благодарим за внимание.</TxtStyle0_Russian><TxtStyle0_German>Danke.</TxtStyle0_German><Separator>@</Separator></Announcement><Announcement><TxtStyle2>Неопознанный багаж (СБ или PRAM) (дневной/ночной рейс)</TxtStyle2></Announcement><Announcement><TxtStyle0_Russian>Дамы и господа!</TxtStyle0_Russian><TxtStyle0_German>Meine Damen und Herren!</TxtStyle0_German><Separator>@</Separator></Announcement><Announcement><TxtStyle0_Russian>В целях обеспечения безопасности полета просим вас выйти из самолета и опознать свой багаж.</TxtStyle0_Russian><TxtStyle0_German>Aus Sicherheitsgründen möchten wir Sie bitten, das Flugzeug zu verlassen und Ihr Gepäck zu identifizieren.</TxtStyle0_German><Separator>@</Separator></Announcement><Announcement><TxtStyle0_Russian>Неопознанный багаж останется в аэропорту.</TxtStyle0_Russian><TxtStyle0_German>Nicht identifizierte Gepäckstücke werden am Flughafen zurückgelassen.</TxtStyle0_German><Separator>@</Separator></Announcement><Announcement><TxtStyle0_Russian>Приносим вам свои извинения за причиненные неудобства.</TxtStyle0_Russian><TxtStyle0_German>Wir entschuldigen uns dafür, und bitten um Ihr Verständnis.</TxtStyle0_German><Separator>@</Separator></Announcement><Announcement><TxtStyle0_Russian>Благодарим за внимание.</TxtStyle0_Russian><TxtStyle0_German>Danke.</TxtStyle0_German><Separator>@</Separator></Announcement><Announcement><TxtStyle7>Информация в полете</TxtStyle7></Announcement><Announcement><TxtStyle2>Нарушение пассажиром правил поведения на борту ВС (СБ или PRAM) (дневной/ночной рейс)</TxtStyle2></Announcement><Announcement><TxtStyle0_Russian>Дамы и господа!</TxtStyle0_Russian><TxtStyle0_German>Meine Damen und Herren!</TxtStyle0_German><Separator>@</Separator></Announcement><Announcement><TxtStyle4>В случае курения</TxtStyle4></Announcement><Announcement><TxtStyle0_Russian>Экипаж обнаружил табачный дым в туалетной комнате.</TxtStyle0_Russian><TxtStyle0_German>Die Besatzung hat Tabakrauch in der Bordtoilette entdeckt.</TxtStyle0_German><Separator>@</Separator></Announcement><Announcement><TxtStyle4>В случае распития алкогольных напитков</TxtStyle4></Announcement><Announcement><TxtStyle0_Russian>Напоминаем вам, что на борту самолета запрещено употребление алкогольных напитков, принесенных с собой.</TxtStyle0_Russian><TxtStyle0_German>Dürfen wir Sie daran erinnern, dass der Konsum alkoholischer Getränke, die Sie an Bord mitgebracht haben, verboten ist.</TxtStyle0_German><Separator>@</Separator></Announcement><Announcement><TxtStyle4>В случае курения/распития алкогольных напитков</TxtStyle4></Announcement><Announcement><TxtStyle0_Russian>Обращаем ваше внимание, что в соответствии со статьей 107 Воздушного кодекса Российской Федерации в случае нарушения пассажиром правил поведения на борту и невыполнения требований экипажа воздушного судна, авиакомпания вправе применить следующие санкции:</TxtStyle0_Russian><TxtStyle0_German>Im Rahmen der russischen Luftfahrtbestimmungen, Artikel 107, können Fluggesellschaften folgende Maßnahmen gegen Passagiere ergreifen, die sich den Verhaltensregeln oder den Anweisungen der Besatzung widersetzen:</TxtStyle0_German><Separator>@</Separator></Announcement><Announcement><TxtStyle0_Russian>передать пассажира в правоохранительные органы в аэропорту прибытия;</TxtStyle0_Russian><TxtStyle0_German>Übergabe an die Strafverfolgungsbehörden am Ankunftsflughafen;</TxtStyle0_German><Separator>@</Separator></Announcement><Announcement><TxtStyle0_Russian>аннулировать договор о перевозке без компенсации его стоимости.</TxtStyle0_Russian><TxtStyle0_German>Kündigung des Luftbeförderungsvertrags ohne Entschädigung.</TxtStyle0_German><Separator>@</Separator></Announcement><Announcement><TxtStyle0_Russian>С «Правилами поведения пассажиров на борту» вы можете ознакомиться в журнале «Аэрофлот».</TxtStyle0_Russian><TxtStyle0_German>Die Verhaltensregeln für Luftfahrtpassagiere entnehmen Sie bitte Ihrem „Aeroflot“-Magazin.</TxtStyle0_German><Separator>@</Separator></Announcement><Announcement><TxtStyle0_Russian>Благодарим за внимание.</TxtStyle0_Russian><TxtStyle0_German>Danke.</TxtStyle0_German><Separator>@</Separator></Announcement><Announcement><TxtStyle2>Получение покупок Duty Free при вылете из городов США (СБ) (дневной/ночной рейс)</TxtStyle2></Announcement><Announcement><TxtStyle0_Russian>Дамы и господа!</TxtStyle0_Russian><TxtStyle0_German>Meine Damen und Herren!</TxtStyle0_German><Separator>@</Separator></Announcement><Announcement><TxtStyle0_Russian>Вы можете получить товары, приобретенные в магазине Duty Free, в переднем/среднем вестибюле.</TxtStyle0_Russian><TxtStyle0_German>Falls Sie Artikel im Duty Free Shop gekauft haben, holen Sie diese bitte im vorderen/mittleren Bereich der Kabine ab.</TxtStyle0_German><Separator>@</Separator></Announcement><Announcement><TxtStyle0_Russian>Благодарим за внимание.</TxtStyle0_Russian><TxtStyle0_German>Danke.</TxtStyle0_German><Separator>@</Separator></Announcement><Announcement><TxtStyle2>Транспортные услуги (СБ) (дневной/ночной рейс)</TxtStyle2></Announcement><Announcement><TxtStyle0_Russian>Дамы и господа!</TxtStyle0_Russian><TxtStyle0_German>Meine Damen und Herren!</TxtStyle0_German><Separator>@</Separator></Announcement><Announcement><TxtStyle0_Russian>Если в аэропорту вы желаете воспользоваться услугами такси по специальным тарифам для пассажиров Аэрофлота, обратитесь к бортпроводникам… [выбрать необходимое]:</TxtStyle0_Russian><TxtStyle0_German>Falls Sie ein Taxi mit dem Sonderfahrpreis für die Aeroflotfluggäste zum Flughafengebäude bestellen möchten,melden Sie sich, bitte,… [выбрать необходимое]:</TxtStyle0_German><Separator>@</Separator></Announcement><Announcement><TxtStyle4>для рейсов короткой продолжительности</TxtStyle4></Announcement><Announcement><TxtStyle6_Russian>при выходе из самолета;</TxtStyle6_Russian><TxtStyle6_German>beim Verlassen des Flugzeugs bei einem Ihrer Flugbegleiter;</TxtStyle6_German><Separator>@</Separator></Announcement><Announcement><TxtStyle4>для рейсов средней и длительной продолжительности</TxtStyle4></Announcement><Announcement><TxtStyle6_Russian>до начала снижения самолета.</TxtStyle6_Russian><TxtStyle6_German>bevor das Flugzeug den Landeanflug beginnt.</TxtStyle6_German><Separator>@</Separator></Announcement><Announcement><TxtStyle0_Russian>Благодарим за внимание.</TxtStyle0_Russian><TxtStyle0_German>Danke.</TxtStyle0_German><Separator>@</Separator></Announcement><Announcement><TxtStyle2>Анкетирование пассажиров (СБ или PRAM) (дневной/ночной рейс)</TxtStyle2></Announcement><Announcement><TxtStyle0_Russian>Дамы и господа!</TxtStyle0_Russian><TxtStyle0_German>Meine Damen und Herren!</TxtStyle0_German><Separator>@</Separator></Announcement><Announcement><TxtStyle0_Russian>Благодарим вас за выбор авиакомпании «Аэрофлот – российские авиалинии».</TxtStyle0_Russian><TxtStyle0_German>Wir bedanken uns, dass Sie heute mit „Aeroflot – Russian Airlines“ geflogen sind.</TxtStyle0_German><Separator>@</Separator></Announcement><Announcement><TxtStyle0_Russian>Нам важно знать ваше мнение о качестве предоставляемых услуг – мы хотим сделать его лучше.</TxtStyle0_Russian><TxtStyle0_German>Wir würden gerne Ihre Kommentare über unseren Service in Erfahrung bringen, damit wir unsere Dienstleistungen noch weiter verbessern können.</TxtStyle0_German><Separator>@</Separator></Announcement><Announcement><TxtStyle0_Russian>Будем благодарны, если вы заполните нашу анкету и передадите ее бортпроводникам.</TxtStyle0_Russian><TxtStyle0_German>Wir wären Ihnen dankbar, wenn Sie unseren Fragebogen ausfüllen und einem Ihren Flugbegleiter geben könnten.</TxtStyle0_German><Separator>@</Separator></Announcement><Announcement><TxtStyle0_Russian>Благодарим за внимание.</TxtStyle0_Russian><TxtStyle0_German>Danke.</TxtStyle0_German><Separator>@</Separator></Announcement><Announcement><TxtStyle2>Отсутствие воды</TxtStyle2></Announcement><Announcement><TxtStyle3>Отсутствие воды – напитки (СБ или PRAM) (дневной/ночной рейс)</TxtStyle3></Announcement><Announcement><TxtStyle0_Russian>Дамы и господа!</TxtStyle0_Russian><TxtStyle0_German>Meine Damen und Herren!</TxtStyle0_German><Separator>@</Separator></Announcement><Announcement><TxtStyle0_Russian>Мы предложим вам прохладительные напитки вместо горячих в связи с отсутствием воды в системе водоснабжения кухонь.</TxtStyle0_Russian><TxtStyle0_German>Wegen Wasserknappheit in der Bordküche können wir Ihnen nur Erfrischungsgetränke anbieten.</TxtStyle0_German><Separator>@</Separator></Announcement><Announcement><TxtStyle0_Russian>Приносим вам свои извинения за причиненные неудобства.</TxtStyle0_Russian><TxtStyle0_German>Wir entschuldigen uns dafür, und bitten um Ihr Verständnis.</TxtStyle0_German><Separator>@</Separator></Announcement><Announcement><TxtStyle0_Russian>Благодарим за внимание.</TxtStyle0_Russian><TxtStyle0_German>Danke.</TxtStyle0_German><Separator>@</Separator></Announcement><Announcement><TxtStyle3>Отсутствие воды – туалеты (СБ) (дневной/ночной рейс)</TxtStyle3></Announcement><Announcement><TxtStyle0_Russian>Дамы и господа!</TxtStyle0_Russian><TxtStyle0_German>Meine Damen und Herren.</TxtStyle0_German><Separator>@</Separator></Announcement><Announcement><TxtStyle0_Russian>В связи с отсутствием воды в системе водоснабжения… [выбрать необходимое]:</TxtStyle0_Russian><TxtStyle0_German>Wegen Wasserknappheit sind die Bordtoiletten… [выбрать необходимое]:</TxtStyle0_German><Separator>@</Separator></Announcement><Announcement><TxtStyle6_Russian>туалет(ы) в передней/средней/хвостовой части самолета в течение/до окончания рейса работать не будет (не будут). Можете пользоваться туалетом (туалетами) в передней/средней/хвостовой части самолета;</TxtStyle6_Russian><TxtStyle6_German>im vorderen/mittleren/hinteren Bereich des Flugzeugs außer Betrieb/ während des gesamten Fluges außer Betrieb. Sie können jedoch die Bordtoiletten im vorderen/mittleren/hinteren Bereich des Flugzeugs benutzen;</TxtStyle6_German><Separator>@</Separator></Announcement><Announcement><TxtStyle6_Russian>все туалеты на борту самолета работать не будут. Поэтому мы совершаем вынужденную посадку в аэропорту… [название аэропорта] города… [название города].</TxtStyle6_Russian><TxtStyle6_German>in allen Bereichen des Flugzeugs außer Betrieb. Wir werden deshalb auf dem… [название аэропорта] Flughafen in… [название города] eine Frühlandung machen.</TxtStyle6_German><Separator>@</Separator></Announcement><Announcement><TxtStyle0_Russian>Приносим вам свои извинения за причиненные неудобства.</TxtStyle0_Russian><TxtStyle0_German>Wir entschuldigen uns dafür, und bitten um Ihr Verständnis.</TxtStyle0_German><Separator>@</Separator></Announcement><Announcement><TxtStyle0_Russian>Благодарим за внимание.</TxtStyle0_Russian><TxtStyle0_German>Danke.</TxtStyle0_German><Separator>@</Separator></Announcement><Announcement><TxtStyle2>Неисправность светового табло (СБ) (дневной/ночной рейс)</TxtStyle2></Announcement><Announcement><TxtStyle0_Russian>Дамы и господа!</TxtStyle0_Russian><TxtStyle0_German>Meine Damen und Herren.</TxtStyle0_German><Separator>@</Separator></Announcement><Announcement><TxtStyle0_Russian>В связи с неисправностью светового табло… [указать, например, «Застегните ремни», «Выключить мобильные телефоны»] просим вас внимательно следить за информационными сообщениями и следовать указаниям экипажа.</TxtStyle0_Russian><TxtStyle0_German>Wegen des Ausfalls des Leuchtzeichens… [указать: „Sicherheitsgurte anschnallen“, „Mobilfunk nicht zulässig“, „Rauchen verboten“], bitten wir Sie den Informationsberichten und den Anweisungen der Flugzeugbesatzung unbedingt zu folgen.</TxtStyle0_German><Separator>@</Separator></Announcement><Announcement><TxtStyle0_Russian>Приносим вам свои извинения за причиненные неудобства.</TxtStyle0_Russian><TxtStyle0_German>Wir entschuldigen uns dafür, und bitten um Ihr Verständnis.</TxtStyle0_German><Separator>@</Separator></Announcement><Announcement><TxtStyle0_Russian>Благодарим за внимание.</TxtStyle0_Russian><TxtStyle0_German>Danke.</TxtStyle0_German><Separator>@</Separator></Announcement><Announcement><TxtStyle2>Невозможность предоставления питания и торгового обслуживания из-за недостатка времени (СБ) (дневной/ночной рейс)</TxtStyle2></Announcement><Announcement><TxtStyle0_Russian>Дамы и господа!</TxtStyle0_Russian><TxtStyle0_German>Meine Damen und Herren!</TxtStyle0_German><Separator>@</Separator></Announcement><Announcement><TxtStyle0_Russian>Время, оставшееся до посадки, не позволяет нам продолжить… [выбрать необходимое]:</TxtStyle0_Russian><TxtStyle0_German>Da wir in Kürze landen, haben wir keine Zeit mehr, um… [выбрать необходимое]:</TxtStyle0_German><Separator>@</Separator></Announcement><Announcement><TxtStyle6_Russian>обслуживание питанием;</TxtStyle6_Russian><TxtStyle6_German>weitere Mahlzeiten zu servieren;</TxtStyle6_German><Separator>@</Separator></Announcement><Announcement><TxtStyle6_Russian>продажу товаров «Sky Shop».</TxtStyle6_Russian><TxtStyle6_German>Artikel aus dem „Sky Shop“ zu verkaufen.</TxtStyle6_German><Separator>@</Separator></Announcement><Announcement><TxtStyle0_Russian>Приносим вам свои извинения за причиненные неудобства.</TxtStyle0_Russian><TxtStyle0_German>Wir entschuldigen uns dafür, und bitten um Ihr Verständnis.</TxtStyle0_German><Separator>@</Separator></Announcement><Announcement><TxtStyle0_Russian>Благодарим за внимание.</TxtStyle0_Russian><TxtStyle0_German>Danke.</TxtStyle0_German><Separator>@</Separator></Announcement><Announcement><TxtStyle2>Образование конденсата в пассажирском салоне в жаркое время года (СБ или PRAM) (дневной/ночной рейс)</TxtStyle2></Announcement><Announcement><TxtStyle0_Russian>Дамы и господа!</TxtStyle0_Russian><TxtStyle0_German>Meine Damen und Herren!</TxtStyle0_German><Separator>@</Separator></Announcement><Announcement><TxtStyle0_Russian>Конденсат, который вы наблюдаете в салоне, образовался в результате работы системы кондиционирования воздуха. Просим вас не беспокоиться.</TxtStyle0_Russian><TxtStyle0_German>Die in der Kabine aufgetretene Kondensation ist von der Klimaanlage verursacht worden. Es besteht kein Grund zur Besorgnis.</TxtStyle0_German><Separator>@</Separator></Announcement><Announcement><TxtStyle0_Russian>Благодарим за внимание.</TxtStyle0_Russian><TxtStyle0_German>Danke.</TxtStyle0_German><Separator>@</Separator></Announcement><Announcement><TxtStyle2>Необходимость медицинской помощи (СБ или PRAM) (дневной/ночной рейс)</TxtStyle2></Announcement><Announcement><TxtStyle0_Russian>Дамы и господа!</TxtStyle0_Russian><TxtStyle0_German>Meine Damen und Herren!</TxtStyle0_German><Separator>@</Separator></Announcement><Announcement><TxtStyle0_Russian>Одному из пассажиров (срочно) требуется медицинская помощь.</TxtStyle0_Russian><TxtStyle0_German>Ein Mitreisender/ eine Mitreisende benötigt (dringend) ärztliche Hilfe.</TxtStyle0_German><Separator>@</Separator></Announcement><Announcement><TxtStyle0_Russian>Если среди вас есть медицинский работник, просим сообщить бортпроводникам.</TxtStyle0_Russian><TxtStyle0_German>Falls sich ein Arzt oder ein medizinisch ausgebildeter Passagier an Bord befindet, melden Sie sich bitte beim Kabinenpersonal.</TxtStyle0_German><Separator>@</Separator></Announcement><Announcement><TxtStyle0_Russian>Нам (очень) необходима Ваша помощь.</TxtStyle0_Russian><TxtStyle0_German>Wir benötigen (dringend) Ihre Hilfe.</TxtStyle0_German><Separator>@</Separator></Announcement><Announcement><TxtStyle0_Russian>Благодарим за внимание.</TxtStyle0_Russian><TxtStyle0_German>Danke.</TxtStyle0_German><Separator>@</Separator></Announcement><Announcement><TxtStyle2>Необходимость использования средств защиты при обнаружении больного на борту ВС (СБ) (дневной/ночной рейс)</TxtStyle2></Announcement><Announcement><TxtStyle0_Russian>Дамы и господа!</TxtStyle0_Russian><TxtStyle0_German>Meine Damen und Herren!</TxtStyle0_German><Separator>@</Separator></Announcement><Announcement><TxtStyle0_Russian>На борту находится пассажир с подозрением на инфекционное заболевание.</TxtStyle0_Russian><TxtStyle0_German>An Bord unseres Flugzeugs befindet sich ein Mitreisender (eine Mitreisende), der (die)bei uns Verdacht erregt, infiziert worden zu sein.</TxtStyle0_German><Separator>@</Separator></Announcement><Announcement><TxtStyle0_Russian>Для обеспечения выполнения требований российских и международных организаций здравоохранения и защиты здоровья пассажиров бортпроводники раздадут вам индивидуальные маски.</TxtStyle0_Russian><TxtStyle0_German>Um die Gesundheit der Fluggäste zu schützen und die Erfüllung der Anforderungen der Russischen und Internationalen Gesundheitsorgáne zu gewährleisten, geben die Flugbegleiter Ihnen die persönlichen Masken aus.</TxtStyle0_German><Separator>@</Separator></Announcement><Announcement><TxtStyle0_Russian>Просим вас занять свое кресло, надеть маску и оставаться в ней до окончания рейса.</TxtStyle0_Russian><TxtStyle0_German>Bitte, kehren Sie zu Ihrem Sitzplatz zurück und legen Sie, bitte, die Maske an. Wir bitten Sie mit der angelegten Maske bis zum Ende des Flugs zu bleiben.</TxtStyle0_German><Separator>@</Separator></Announcement><Announcement><TxtStyle4>При раздаче всем пассажирам «Формы представления информации»/«Анкеты прибывающего»</TxtStyle4></Announcement><Announcement><TxtStyle0_Russian>В соответствии с требованиями органов здравоохранения вам необходимо заполнить медицинские формуляры.</TxtStyle0_Russian><TxtStyle0_German>In wenigen Minuten geben wir Ihnen die Formulare aus, die Sie laut der Forderung der Gesundheitsorgane ausfüllen müssen.</TxtStyle0_German><Separator>@</Separator></Announcement><Announcement><TxtStyle0_Russian>Формуляры должны быть заполнены печатными заглавными буквами с обязательным указанием адреса места пребывания в течение 30 дней с даты въезда.</TxtStyle0_Russian><TxtStyle0_German>Die Formulare werden mit Druckbuchstaben ausgefüllt. Die Adresse Ihres Aufenthalts im Laufe von nächsten 30 Tagen seit dem Einreisedatum ist erforderlich zum ausfüllen.</TxtStyle0_German><Separator>@</Separator></Announcement><Announcement><TxtStyle0_Russian>Просим вас передать заполненные формуляры бортпроводникам до выхода из самолета.</TxtStyle0_Russian><TxtStyle0_German>Wir bitten Sie, die ausgefüllten Formulare den Flugbegleitern vor dem Verlassen des Flugzeugs zu geben.</TxtStyle0_German><Separator>@</Separator></Announcement><Announcement><TxtStyle4>Общая информация</TxtStyle4></Announcement><Announcement><TxtStyle0_Russian>Если вам нужна помощь или вы почувствовали недомогание, обращайтесь к бортпроводникам.</TxtStyle0_Russian><TxtStyle0_German>Wenn Ihnen etwas fehlt und Sie sich nicht wohl fühlen, oder falls Sie Hilfe brauchen, melden Sie sich bitte sofort bei einem Ihrer Flugbegleiter.</TxtStyle0_German><Separator>@</Separator></Announcement><Announcement><TxtStyle0_Russian>Благодарим за внимание.</TxtStyle0_Russian><TxtStyle0_German>Danke.</TxtStyle0_German><Separator>@</Separator></Announcement><Announcement><TxtStyle2>Розыск и нахождение потерянных вещей (СБ) (дневной/ночной рейс)</TxtStyle2></Announcement><Announcement><TxtStyle0_Russian>Дамы и господа!</TxtStyle0_Russian><TxtStyle0_German>Meine Damen und Herren!</TxtStyle0_German><Separator>@</Separator></Announcement><Announcement><TxtStyle4>Розыск потерянных вещей</TxtStyle4></Announcement><Announcement><TxtStyle0_Russian>Мы разыскиваем… [указать что именно], потерянный (потерянную/-ое/-ые) одним из пассажиров. Если вы его (ее, их) найдете, просим передать бортпроводникам.</TxtStyle0_Russian><TxtStyle0_German>Wir suchen nach einem/einer/ … [указать что именно], der/das/die von einem Mitreisenden verloren wurde. Falls Sie ihn/es/sie finden, übergeben Sie ihn/es/sie bitte dem Kabinenpersonal.</TxtStyle0_German><Separator>@</Separator></Announcement><Announcement><TxtStyle0_Russian>Благодарим за внимание.</TxtStyle0_Russian><TxtStyle0_German>Danke.</TxtStyle0_German><Separator>@</Separator></Announcement><Announcement><TxtStyle4>Нахождение потерянных вещей</TxtStyle4></Announcement><Announcement><TxtStyle0_Russian>В… [указать где: салоне, туалетной комнате, др.] найден (найдена/-о) … [указать что именно]. Если он (она, оно) принадлежит вам, пожалуйста, обратитесь к бортпроводникам.</TxtStyle0_Russian><TxtStyle0_German>Ein/eine… [указать что именно] ist in der/dem… [указать где: Kabine, Toilette, др.] gefunden worden. Falls Sie ihn/es/ sie verloren haben könnten, melden Sie sich bitte beim Kabinenpersonal.</TxtStyle0_German><Separator>@</Separator></Announcement><Announcement><TxtStyle0_Russian>Благодарим за внимание.</TxtStyle0_Russian><TxtStyle0_German>Danke.</TxtStyle0_German><Separator>@</Separator></Announcement><Announcement><TxtStyle2>Изменение маршрута полета (КВС или СБ по указанию КВС) (дневной/ночной рейс)</TxtStyle2></Announcement><Announcement><TxtStyle0_Russian>Дамы и господа!</TxtStyle0_Russian><TxtStyle0_German>Meine Damen und Herren.</TxtStyle0_German><Separator>@</Separator></Announcement><Announcement><TxtStyle0_Russian>Говорит командир корабля. (Командир корабля сообщил, что…) [выбрать необходимое]:</TxtStyle0_Russian><TxtStyle0_German>Hier spricht Ihr Kapitän. (Der Kapitän hat uns folgendes mitgeteilt…) [выбрать необходимое]:</TxtStyle0_German><Separator>@</Separator></Announcement><Announcement><TxtStyle0_Russian>По метеоусловиям аэропорта… [название аэропорта] города … [название аэропорта];</TxtStyle0_Russian><TxtStyle0_German>Wegen der Wetterbedingungen am Flughafen… [название аэропорта];</TxtStyle0_German><Separator>@</Separator></Announcement><Announcement><TxtStyle0_Russian>В связи с производственными причинами;</TxtStyle0_Russian><TxtStyle0_German>Aus betriebsbedingten Gründen;</TxtStyle0_German><Separator>@</Separator></Announcement><Announcement><TxtStyle0_Russian>В связи с тем, что одному из пассажиров на борту требуется медицинская помощь,</TxtStyle0_Russian><TxtStyle0_German>Um einen Mitreisenden mit ärztlicher Hilfe zu versorgen</TxtStyle0_German><Separator>@</Separator></Announcement><Announcement><TxtStyle0_Russian>мы совершим посадку в ближайшем аэропорту города… [название города].</TxtStyle0_Russian><TxtStyle0_German>werden wir auf dem nächstmöglichen Flughafen in… [название города] landen.</TxtStyle0_German><Separator>@</Separator></Announcement><Announcement><TxtStyle0_Russian>Наземные службы аэропорта… [название аэропорта] в… [название города] окажут вам необходимую помощь и содействие.</TxtStyle0_Russian><TxtStyle0_German>Bodenpersonal am Flughafen… [название аэропорта] in… [название города] werden Ihnen bei allen Fragen helfen.</TxtStyle0_German><Separator>@</Separator></Announcement><Announcement><TxtStyle0_Russian>Приносим вам свои извинения за причиненные неудобства.</TxtStyle0_Russian><TxtStyle0_German>Wir entschuldigen uns dafür, und bitten um Ihr Verständnis.</TxtStyle0_German><Separator>@</Separator></Announcement><Announcement><TxtStyle0_Russian>Благодарю (благодарим) за внимание.</TxtStyle0_Russian><TxtStyle0_German>Danke.</TxtStyle0_German><Separator>@</Separator></Announcement><Announcement><TxtStyle2>Переруливание в другой терминал аэропорта Шереметьево (СБ) (дневной/ночной рейс)</TxtStyle2></Announcement><Announcement><TxtStyle0_Russian>Дамы и господа!</TxtStyle0_Russian><TxtStyle0_German>Meine Damen und Herren!</TxtStyle0_German><Separator>@</Separator></Announcement><Announcement><TxtStyle0_Russian>Наш самолет совершит посадку в аэропорту Шереметьево, Терминал B/C/D/E/F, из-за загруженности Терминала D/E/F.</TxtStyle0_Russian><TxtStyle0_German>Wegen des hohen Flugaufkommens auf Terminal B/C/D/E/F wird die Maschine auf Scheremetjewo Terminal D/E/F landen.</TxtStyle0_German><Separator>@</Separator></Announcement><Announcement><TxtStyle0_Russian>В зале прилета будет сделано объявление для встречающих.</TxtStyle0_Russian><TxtStyle0_German>Die Ankunftshalle ist informiert.</TxtStyle0_German><Separator>@</Separator></Announcement><Announcement><TxtStyle0_Russian>Приносим вам свои извинения за причиненные неудобства.</TxtStyle0_Russian><TxtStyle0_German>Wir entschuldigen uns dafür, und bitten um Ihr Verständnis.</TxtStyle0_German><Separator>@</Separator></Announcement><Announcement><TxtStyle0_Russian>Благодарим за внимание.</TxtStyle0_Russian><TxtStyle0_German>Danke.</TxtStyle0_German><Separator>@</Separator></Announcement><Announcement><TxtStyle7>После посадки</TxtStyle7></Announcement><Announcement><TxtStyle2>Обработка салона самолета инсектицидами (СБ или PRAM) (дневной/ночной рейс)</TxtStyle2></Announcement><Announcement><TxtStyle0_Russian>Дамы и господа!</TxtStyle0_Russian><TxtStyle0_German>Meine Damen und Herren!</TxtStyle0_German><Separator>@</Separator></Announcement><Announcement><TxtStyle0_Russian>В соответствии с медицинскими требованиями страны прибытия салон будет обработан инсектицидами. Эти препараты соответствуют международным стандартам и не опасны для вашего здоровья.</TxtStyle0_Russian><TxtStyle0_German>Im Rahmen der internationalen Gesundheitsvorschriften muss die Kabine mit einem Insektizid ausgesprüht werden. Diese Substanzen entsprechen den internationalen Richtlinien und sind völlig ungefährlich.</TxtStyle0_German><Separator>@</Separator></Announcement><Announcement><TxtStyle0_Russian>Просим вас не покидать своих мест до окончания обработки.</TxtStyle0_Russian><TxtStyle0_German>Bitte bleiben Sie sitzen, bis der Sprühvorgang beendet ist.</TxtStyle0_German><Separator>@</Separator></Announcement><Announcement><TxtStyle0_Russian>Благодарим за внимание.</TxtStyle0_Russian><TxtStyle0_German>Danke.</TxtStyle0_German><Separator>@</Separator></Announcement><Announcement><TxtStyle2>Проверка посадочных талонов и паспортов на борту после посадки в аэропорту Шереметьево в случае превышения фактического количества пассажиров (СБ) (дневной/ночной рейс)</TxtStyle2></Announcement><Announcement><TxtStyle0_Russian>Дамы и господа!</TxtStyle0_Russian><TxtStyle0_German>Meine Damen und Herren!</TxtStyle0_German><Separator>@</Separator></Announcement><Announcement><TxtStyle0_Russian>По требованию служб аэропорта Шереметьево вам необходимо пройти дополнительный контроль при выходе из самолета.</TxtStyle0_Russian><TxtStyle0_German>Das Bodenpersonal des Flughafens Scheremetjewo führt eine zusätzliche Kontrolle durch.</TxtStyle0_German><Separator>@</Separator></Announcement><Announcement><TxtStyle0_Russian>Просим вас приготовить посадочные талоны и паспорта.</TxtStyle0_Russian><TxtStyle0_German>Halten Sie bitte beim Verlassen des Flugzeugs Ihren Pass und Ihre Bordkarte bereit.</TxtStyle0_German><Separator>@</Separator></Announcement><Announcement><TxtStyle0_Russian>Благодарим за внимание.</TxtStyle0_Russian><TxtStyle0_German>Danke.</TxtStyle0_German><Separator>@</Separator></Announcement><Announcement><TxtStyle2>Необходимость медицинской помощи по прилету, когда пассажиры встают с мест (СБ или PRAM) (дневной/ночной рейс)</TxtStyle2></Announcement><Announcement><TxtStyle0_Russian>Дамы и господа!</TxtStyle0_Russian><TxtStyle0_German>Meine Damen und Herren!</TxtStyle0_German><Separator>@</Separator></Announcement><Announcement><TxtStyle0_Russian>Просим Вас оставаться на своих местах и дать возможность медицинскому персоналу  пройти к пассажиру для оказания медицинской помощи. О начале высадки из самолета мы вас проинформируем.</TxtStyle0_Russian><TxtStyle0_German>Wir bitten Sie auf Ihren Plätzen zu bleiben, um dem medizinischen Personal einen einfachen Zugang zum Fluggast, der eine medizinische Versorgung braucht, bereitzustellen. Über den Beginn des Aussteigens warden wir Sie informieren.</TxtStyle0_German><Separator>@</Separator></Announcement><Announcement><TxtStyle0_Russian>Благодарю за понимание.</TxtStyle0_Russian><TxtStyle0_German>Danke.</TxtStyle0_German><Separator>@</Separator></Announcement></Handbook></Root>
